AUTHORS.rst
CONTRIBUTING.rst
HISTORY.rst
LICENSE
MANIFEST.in
README.rst
gsshcli.py
setup.cfg
setup.py
gerritssh/METADATA
gerritssh/__init__.py
gerritssh/bancommit.py
gerritssh/gerritsite.py
gerritssh/lsgroups.py
gerritssh/lsmembers.py
gerritssh/lsprojects.py
gerritssh/query.py
gerritssh/review.py
gerritssh.egg-info/PKG-INFO
gerritssh.egg-info/SOURCES.txt
gerritssh.egg-info/dependency_links.txt
gerritssh.egg-info/not-zip-safe
gerritssh.egg-info/requires.txt
gerritssh.egg-info/top_level.txt
gerritssh/borrowed/__init__.py
gerritssh/borrowed/ssh.py
gerritssh/internal/__init__.py
gerritssh/internal/cmdoptions.py
test/test_bancommit.py
test/test_lsgroups.py
test/test_lsmembers.py
test/test_misc.py
test/test_online.py
test/test_options.py
test/test_query.py
test/test_reviews.py
test/test_site.py