Metadata-Version: 1.1
Name: gerritssh
Version: 0.1.3
Summary: Python package wrapping the Gerrit command line API
Home-page: https://github.com/kdopen/gerritssh
Author: Keith Derrick
Author-email: kderrick_public@att.net
License: Apache
Keywords: gerritssh
Platform: UNKNOWN
Classifier: Development Status :: 2 - Pre-Alpha
Classifier: Intended Audience :: Developers
Classifier: License :: OSI Approved :: Apache Software License
Classifier: Natural Language :: English
Classifier: Operating System :: MacOS :: MacOS X
Classifier: Operating System :: POSIX :: Linux
Classifier: Programming Language :: Python :: 2
Classifier: Programming Language :: Python :: 2.6
Classifier: Programming Language :: Python :: 2.7
Classifier: Programming Language :: Python :: 3
Classifier: Programming Language :: Python :: 3.3
Classifier: Programming Language :: Python :: 3.4
